pydantic_loggings/__init__.py
pydantic_loggings/mixins.py
pydantic_loggings/types_.py
pydantic_loggings/utils.py
pydantic_loggings/base/__init__.py
pydantic_loggings/base/filters.py
pydantic_loggings/base/formatters.py
pydantic_loggings/base/handlers.py
pydantic_loggings/base/loggers.py
pydantic_loggings/base/loggings.py
pydantic_loggings/not_set/__init__.py
pydantic_loggings/not_set/filters.py
pydantic_loggings/not_set/formatters.py
pydantic_loggings/not_set/handlers.py
pydantic_loggings/not_set/loggers.py
pydantic_loggings/not_set/loggings.py
pydantic_loggings/rich/__init__.py
pydantic_loggings/rich/filters.py
pydantic_loggings/rich/formatters.py
pydantic_loggings/rich/handlers.py
pydantic_loggings/rich/loggers.py
pydantic_loggings/rich/loggings.py
pydantic_loggings-1.6.1.dist-info/METADATA
pydantic_loggings-1.6.1.dist-info/WHEEL
pydantic_loggings-1.6.1.dist-info/top_level.txt
pydantic_loggings-1.6.1.dist-info/RECORD
