Metadata-Version: 2.1
Name: pydantic-loggings
Version: 1.6.1
Summary: Configure 🎁 Your 🤗 Python 🐍 Logging 📝
Author-email: m9810223 <m9810223@gmail.com>
Project-URL: Homepage, https://github.com/m9810223/pydantic-loggings
Project-URL: Source, https://github.com/m9810223/pydantic-loggings
Classifier: Programming Language :: Python :: 3.11
Classifier: Programming Language :: Python :: 3.10
Classifier: Programming Language :: Python :: 3.9
Classifier: Programming Language :: Python :: 3.8
Classifier: Programming Language :: Python :: 3
Classifier: Programming Language :: Python :: 3 :: Only
Classifier: Typing :: Typed
Classifier: Framework :: Pydantic
Classifier: Framework :: Pydantic :: 2
Classifier: Environment :: Console
Requires-Python: >=3.9
Requires-Dist: pydantic (>=2.0)
Requires-Dist: pydantic-settings (>=2.0)
Provides-Extra: rich
Requires-Dist: rich (>=13.4.2) ; extra == 'rich'
